{
  "heading": "パンダの魅惑的な世界を発見する",
  "introduction": "はじめに",
  "introduction_p": "パンダは、その愛らしい容姿と穏やかな態度で、世界中の人々の心に特別な場所を持っています。これらのカリスマ溢れる生物は、保護活動の愛される象徴であり、野生動物の保護のための大使でもあります。パンダの魅力的な世界に没頭し、その生息地、行動、そして彼らの保存を目指す重要な保護活動を探ってみましょう。",
  "appearance": "外見",
  "appearance_p": "巨大なパンダ、学術的にはアイルロポーダ メラノレウカとして知られる彼らは、その独特な白黒の毛皮で一目で分かります。ふくよかな体と魅惑的な丸い顔で、パンダはあらゆる年齢の人々を魅了します。",
  "habitat": "生息地",
  "habitat_p": "パンダは中国の中央部の山岳地帯、特に四川、陝西、甘粛省に生息しています。彼らの生息地は密な竹の森で構成され、食糧と避難所を見つける場所です。これらの森はパンダの孤独で平和な生活スタイルに最適な背景を提供しています。",
  "diet": "食事",
  "diet_p": "主に草食動物であるパンダは、竹の愛好者です。彼らの食事はほとんどがさまざまな竹の種類で構成され、時折小動物、鳥、または死肉といったものが補足されます。驚くべきことに、パンダは毎日膨大な量の竹を摂取し、必要な栄養を取得する柔軟性を披露しています。",
  "solitary_nature": "孤独な性格",
  "solitary_nature_p": "パンダはその孤独な性格で知られており、成体は通常、繁殖シーズン以外ではお互いを避ける傾向があります。独立した生活様式にもかかわらず、パンダは鳴き声、臭いのマーキング、そして時折の相互作用を通じて社会的なダイナミクスを見せています。",
  "survival_threats": "生存の脅威",
  "survival_threats_p": "パンダは世界中の人々を魅了しましたが、彼らは生存に多くの脅威に直面しています。人間の侵入による生息地の喪失、竹の利用可能性への気候変動、密猟などが、これらの象徴的な動物が直面する課題に寄与しています。",
  "copyright": "© 2023 マルチリンガル パンダ ワールド。全著作権所有。"
}